{
    "id": 286971,
    "api_model": "products",
    "api_link": "https://api.artic.edu/api/v1/products/286971",
    "title": "Shape Stamps Set",
    "external_sku": 286971,
    "image_url": "https://shop-images.imgix.net/286971_2.jpg",
    "web_url": "https://shop.artic.edu/products/286971",
    "description": "Shape Stamps invite you to see more than the shapes in front of you. Layer, overlap, and connect their various forms to create characters, landscapes, or still life masterpieces. Dab and press however you see fit to imagine endless designs and compositions.<br data-mce-fragment=\"1\"><br data-mce-fragment=\"1\">Includes thirteen different shapes and five ink pads. Fun tip: Wipe your stamps with a damp cloth between uses to keep them clean and avoid mixing colors on the ink pad. This will ensure each mark you make is bright and clear.<br data-mce-fragment=\"1\"><ul><li><strong>Dimensions:&nbsp;</strong>Each stamp varies in size</li><li><strong>Materials:</strong> Beech wood, rubber</li><li><strong>Ages 6+</strong></li></ul>",
    "price_display": "<p>$29.95 <s>$0</s></p>",
    "min_compare_at_price": 0,
    "max_compare_at_price": 0,
    "min_current_price": 29.95,
    "max_current_price": 29.95,
    "artist_ids": [],
    "artwork_ids": [],
    "exhibition_ids": [],
    "source_updated_at": "2023-09-23T08:30:16-05:00",
    "updated_at": "2023-09-23T23:10:42-05:00",
    "timestamp": "2023-09-24T02:12:16-05:00"
}