{
    "id": 100253,
    "api_model": "artworks",
    "api_link": "https://api.artic.edu/api/v1/artworks/100253",
    "is_boosted": false,
    "title": "An Untitled Print",
    "alt_titles": null,
    "thumbnail": {
        "lqip": "data:image/gif;base64,R0lGODlhAgAFAPMAALq5try7ucG/u8nHw9XSy9bTzdfUztjVzt/b1OPf2AAAAAAAAAAAAAAAAAAAAAAAACH5BAAAAAAALAAAAAACAAUAAAQI8CRTAhADkQgAOw==",
        "width": 6075,
        "height": 13310,
        "alt_text": "A work made of lithograph from fourteen plates in blue and green ink on white wove paper."
    },
    "main_reference_number": "1983.269",
    "has_not_been_viewed_much": true,
    "boost_rank": null,
    "date_start": 1981,
    "date_end": 1982,
    "date_display": "1981\u201382",
    "date_qualifier_title": "",
    "date_qualifier_id": null,
    "artist_display": "Lee Bontecou (American, 1931-2022)\nprinted by Thomas Cox and James V. Smith\npublished by Universal Limited Art Editions (American, founded 1955)",
    "place_of_origin": "United States",
    "description": "<p>The largest and most ambitious print of Bontecou\u2019s career, the magisterial <em>An Untitled Print</em> was made from 14 plates and rivals her sculptures, if only in size. This offset lithograph was produced from metal plates instead of lithographic stones; the image on the plates was transferred (\u201coffset\u201d) to a rubber blanket or roller before being printed onto paper.</p>\n",
    "dimensions": "236 \u00d7 106.5 cm (92 15/16 \u00d7 41 15/16 in.)",
    "dimensions_detail": [
        {
            "depth_cm": 0,
            "depth_in": 0,
            "width_cm": 106.5,
            "width_in": 41.9292,
            "height_cm": 236,
            "height_in": 92.9134,
            "diameter_cm": 0,
            "diameter_in": 0,
            "clarification": null
        }
    ],
    "medium_display": "Lithograph from fourteen plates in blue and green ink on white wove paper",
    "inscriptions": null,
    "credit_line": "U.L.A.E. Collection acquired through a challenge grant of Mr. and Mrs. Thomas Dittmer; purchased with funds provided by supporters of the Department of Prints and Drawings; Centennial Endowment; Margaret Fisher Endowment Fund",
    "catalogue_display": "<p>Sparks 34 artist's proof</p>",
    "publication_history": null,
    "exhibition_history": null,
    "provenance_text": null,
    "edition": null,
    "publishing_verification_level": "Web Basic",
    "internal_department_id": 3,
    "fiscal_year": null,
    "fiscal_year_deaccession": null,
    "is_public_domain": false,
    "is_zoomable": false,
    "max_zoom_window_size": 843,
    "copyright_notice": null,
    "has_multimedia_resources": false,
    "has_educational_resources": false,
    "has_advanced_imaging": false,
    "colorfulness": 9.6961,
    "color": {
        "h": 70,
        "l": 51,
        "s": 13,
        "percentage": 0.005459142811818209,
        "population": 85
    },
    "latitude": null,
    "longitude": null,
    "latlon": null,
    "is_on_view": false,
    "on_loan_display": null,
    "gallery_title": null,
    "gallery_id": null,
    "nomisma_id": null,
    "artwork_type_title": "Print",
    "artwork_type_id": 18,
    "department_title": "Prints and Drawings",
    "department_id": "PC-13",
    "artist_id": 30617,
    "artist_title": "Lee Bontecou",
    "alt_artist_ids": [],
    "artist_ids": [
        30617
    ],
    "artist_titles": [
        "Lee Bontecou"
    ],
    "category_ids": [
        "PC-13",
        "PC-825"
    ],
    "category_titles": [
        "Prints and Drawings",
        "Women artists"
    ],
    "term_titles": [
        "lithograph",
        "paper (fiber product)",
        "print",
        "prints and drawing"
    ],
    "style_id": null,
    "style_title": null,
    "alt_style_ids": [],
    "style_ids": [],
    "style_titles": [],
    "classification_id": "TM-71",
    "classification_title": "lithograph",
    "alt_classification_ids": [
        "TM-17",
        "TM-4"
    ],
    "classification_ids": [
        "TM-71",
        "TM-17",
        "TM-4"
    ],
    "classification_titles": [
        "lithograph",
        "print",
        "prints and drawing"
    ],
    "subject_id": null,
    "alt_subject_ids": [],
    "subject_ids": [],
    "subject_titles": [],
    "material_id": "TM-2982",
    "alt_material_ids": [],
    "material_ids": [
        "TM-2982"
    ],
    "material_titles": [
        "paper (fiber product)"
    ],
    "technique_id": null,
    "alt_technique_ids": [],
    "technique_ids": [],
    "technique_titles": [],
    "theme_titles": [
        "Women artists"
    ],
    "image_id": "6b94efb7-b773-198c-ddbb-3945cbc71d47",
    "alt_image_ids": [],
    "document_ids": [],
    "sound_ids": [],
    "video_ids": [],
    "text_ids": [],
    "section_ids": [],
    "section_titles": [],
    "site_ids": [],
    "suggest_autocomplete_all": [
        {
            "input": [
                "1983.269"
            ],
            "contexts": {
                "groupings": [
                    "accession"
                ]
            }
        },
        {
            "input": [
                "An Untitled Print"
            ],
            "weight": 1,
            "contexts": {
                "groupings": [
                    "title"
                ]
            }
        }
    ],
    "source_updated_at": "2022-11-09T09:01:46-06:00",
    "updated_at": "2023-04-07T14:14:35-05:00",
    "timestamp": "2023-09-24T01:04:40-05:00"
}