{
    "id": 103966,
    "api_model": "artworks",
    "api_link": "https://api.artic.edu/api/v1/artworks/103966",
    "is_boosted": false,
    "title": "Eaton's Department Store, Toronto, Canada, Interior Perspective",
    "alt_titles": null,
    "thumbnail": {
        "lqip": "data:image/gif;base64,R0lGODlhAwAFAPMAAI6EbZaLdJuReZ+Ue6OXfqicgaqei62girirkbqulLuwmMG0nNPGsdTHsd/SvAAAACH5BAAAAAAALAAAAAADAAUAAAQLsDmGVCKiBDCOWREAOw==",
        "width": 1294,
        "height": 2250,
        "alt_text": "A work made of pencil on tracing paper."
    },
    "main_reference_number": "1985.118",
    "has_not_been_viewed_much": true,
    "boost_rank": null,
    "date_start": 1912,
    "date_end": 1912,
    "date_display": "1912",
    "date_qualifier_title": "",
    "date_qualifier_id": null,
    "artist_display": "Burnham (D. H.) & Co.\nAmerican, 1896-1912",
    "place_of_origin": "Toronto",
    "description": null,
    "dimensions": "70 \u00d7 40.6 cm (27 9/16 \u00d7 15 15/16 in.)",
    "dimensions_detail": [
        {
            "depth_cm": 0,
            "depth_in": 0,
            "width_cm": 40.6,
            "width_in": 15.9375,
            "height_cm": 70,
            "height_in": 27.5625,
            "diameter_cm": 0,
            "diameter_in": 0,
            "clarification": null
        }
    ],
    "medium_display": "Pencil on tracing paper",
    "inscriptions": null,
    "credit_line": "Purchased with funds provided by the Benefactors of Architecture Endowment Fund",
    "catalogue_display": null,
    "publication_history": null,
    "exhibition_history": null,
    "provenance_text": null,
    "edition": null,
    "publishing_verification_level": "Web Basic",
    "internal_department_id": 25,
    "fiscal_year": null,
    "fiscal_year_deaccession": null,
    "is_public_domain": false,
    "is_zoomable": false,
    "max_zoom_window_size": 843,
    "copyright_notice": null,
    "has_multimedia_resources": false,
    "has_educational_resources": false,
    "has_advanced_imaging": false,
    "colorfulness": 16.3951,
    "color": {
        "h": 41,
        "l": 51,
        "s": 14,
        "percentage": 0.056237144350634954,
        "population": 695
    },
    "latitude": null,
    "longitude": null,
    "latlon": null,
    "is_on_view": false,
    "on_loan_display": null,
    "gallery_title": null,
    "gallery_id": null,
    "nomisma_id": null,
    "artwork_type_title": "Architectural Drawing",
    "artwork_type_id": 34,
    "department_title": "Architecture and Design",
    "department_id": "PC-5",
    "artist_id": 34109,
    "artist_title": "D.H. Burnham & Co.",
    "alt_artist_ids": [],
    "artist_ids": [
        34109
    ],
    "artist_titles": [
        "D.H. Burnham & Co."
    ],
    "category_ids": [
        "PC-5"
    ],
    "category_titles": [
        "Architecture and Design"
    ],
    "term_titles": [
        "storefronts",
        "architectural drawing",
        "pencil",
        "20th Century",
        "drawing",
        "architecture",
        "architecture",
        "perspective",
        "interiors",
        "Canada",
        "perspective",
        "tracing paper"
    ],
    "style_id": "TM-13130",
    "style_title": "20th Century",
    "alt_style_ids": [],
    "style_ids": [
        "TM-13130"
    ],
    "style_titles": [
        "20th Century"
    ],
    "classification_id": "TM-126",
    "classification_title": "architectural drawing",
    "alt_classification_ids": [
        "TM-103",
        "TM-13308"
    ],
    "classification_ids": [
        "TM-126",
        "TM-103",
        "TM-13308"
    ],
    "classification_titles": [
        "architectural drawing",
        "architecture",
        "perspective"
    ],
    "subject_id": "TM-12766",
    "alt_subject_ids": [
        "TM-13376",
        "TM-12085",
        "TM-13373",
        "TM-12285",
        "TM-13333"
    ],
    "subject_ids": [
        "TM-12766",
        "TM-13376",
        "TM-12085",
        "TM-13373",
        "TM-12285",
        "TM-13333"
    ],
    "subject_titles": [
        "storefronts",
        "drawing",
        "architecture",
        "perspective",
        "interiors",
        "Canada"
    ],
    "material_id": "TM-2450",
    "alt_material_ids": [
        "TM-3040"
    ],
    "material_ids": [
        "TM-2450",
        "TM-3040"
    ],
    "material_titles": [
        "pencil",
        "tracing paper"
    ],
    "technique_id": null,
    "alt_technique_ids": [],
    "technique_ids": [],
    "technique_titles": [],
    "theme_titles": [],
    "image_id": "a9b8cf33-6872-45c5-5d94-e4642beb0c3d",
    "alt_image_ids": [],
    "document_ids": [],
    "sound_ids": [],
    "video_ids": [],
    "text_ids": [],
    "section_ids": [],
    "section_titles": [],
    "site_ids": [],
    "suggest_autocomplete_all": [
        {
            "input": [
                "1985.118"
            ],
            "contexts": {
                "groupings": [
                    "accession"
                ]
            }
        },
        {
            "input": [
                "Eaton's Department Store, Toronto, Canada, Interior Perspective"
            ],
            "weight": 7,
            "contexts": {
                "groupings": [
                    "title"
                ]
            }
        }
    ],
    "source_updated_at": "2022-09-21T19:19:07-05:00",
    "updated_at": "2023-04-10T11:27:23-05:00",
    "timestamp": "2023-09-24T01:07:04-05:00"
}