{
    "id": 149022,
    "api_model": "artworks",
    "api_link": "https://api.artic.edu/api/v1/artworks/149022",
    "is_boosted": false,
    "title": "Saint Francis of Assisi Adoring the Virgin and Child",
    "alt_titles": null,
    "thumbnail": {
        "lqip": "data:image/gif;base64,R0lGODlhAwAFAPMAAHJyanZ2bnl2anl2a3t2a3h3bX15bn97cIF6bYB8cIB9cYV+cIWAc6udia2eiQAAACH5BAAAAAAALAAAAAADAAUAAAQLsDFnghIlDXAWQREAOw==",
        "width": 4991,
        "height": 8000,
        "alt_text": "A work made of black chalk on blue laid paper."
    },
    "main_reference_number": "1998.99",
    "has_not_been_viewed_much": false,
    "boost_rank": null,
    "date_start": 1607,
    "date_end": 1607,
    "date_display": "1607",
    "date_qualifier_title": "",
    "date_qualifier_id": null,
    "artist_display": "Denys Calvaert\nFlemish, c. 1540-1619",
    "place_of_origin": "Flanders",
    "description": "<p>This monumental drawing shows Denys Calvaert\u2019s nearly final conception for an altarpiece. The artist made a few intriguing changes before completing the painting. He replaced a child in the lower left of the drawing with an older saint figure, covered the Christ Child\u2019s genitalia, and shifted Saint Francis\u2019s head toward the center of the composition.</p>\n",
    "dimensions": "52.1 \u00d7 31.2 cm (20 9/16 \u00d7 12 5/16 in.)",
    "dimensions_detail": [
        {
            "depth_cm": 0,
            "depth_in": 0,
            "width_cm": 31.2,
            "width_in": 12.2835,
            "height_cm": 52.1,
            "height_in": 20.5119,
            "diameter_cm": 0,
            "diameter_in": 0,
            "clarification": null
        }
    ],
    "medium_display": "Black chalk on blue laid paper",
    "inscriptions": "Inscribed verso, upper left, in graphite: \"101\"; lower left, in graphite: \"D.6924/2\"",
    "credit_line": "Gift of Dorothy Braude Edinburg to the Harry B. and Bessie K. Braude Memorial Collection",
    "catalogue_display": null,
    "publication_history": "D. Stephen Pepper, The Bob Jones University Collection of Religious Art: Italian Paintings (Greenville, SC: Bob Jones University, 1984), p. 39, under cat. 36.1. \n\nDavid H. Steel, Jr., Baroque Paintings from the Bob Jones University Collection, exh. cat. (Raleigh, NC: North Carolina Museum of Art, 1984), p. 34, under cat. 6, fig. 4. \n\nTer\u00e9z Gerszi, \u201cUn Dessin r\u00e9cemment indentifi\u00e9 de Denys Calvaert,\u201d Bulletin du Mus\u00e9e Hongrois des Beaux-Arts 64 (1985), pp. 35\u201342, fig. 19. \n\nGiuliano Briganti et al., The Age of Correggio and the Carracci: Emilian Painting of the Sixteenth and Seventeenth Centuries, exh. cat. (Washington, D.C.: National gallery of Art, 1986\u201387), p. 78, under cat.17.\n\nSimone Twiehaus, Dionisio Calvaert, um 1540\u20131619: Die Altarwerke (Berlin: Reimer, 2002), p. 222, under cat. A26, fig. 57.\n\nMary Vaccaro, \u201cA New Identified Drawing by Denys Calvaert in the Uffizi,\u201d Burlington Magazine 158 (March, 2016), p. 193 (ill).",
    "exhibition_history": "London, Faerber and Maison, Old Master Drawings and Paintings Presented by Yvonne Tan Bunzl, April 6\u201325, 1970, cat. 15 (ill.). \n\nCambridge, Mass., Fogg Art Museum, Harvard University, Italian Drawings and Prints around 1600, Dec. 9, 1974\u2013Feb. 15, 1975. \n\nArt Institute of Chicago, Gifts of a Lifetime: 49 Old Masters Drawings from the Dorothy Braude Edinburg Collection, Dec. 11,1998\u2013Mar. 28,1999, checklist 9.\n\nArt Institute of Chicago, Drawings in Dialogue: Old Master Through Modern, The Harry B. and Bessie K. Braude Memorial Collection, June 3\u2013July 30, 2006, p. 32, cat. 7 (ill.).\n\nThe Art Institute of Chicago, \"Rubens, Rembrandt, and Drawing in the Golden Age\", September 28, 2019 - January 5, 2020, pp. 85 (ill.), 86-87, 292-93 cat. 26, cat. by Victoria Sancho Lobis, et. al.",
    "provenance_text": "Jonathan Richardson, Jr. (1694\u20131771) [stamp (Lugt 2170), recto, lower right, in black]. Yvonne Tan Bunzl, London, by 1970 [London, 1970]; sold to Dorothy Braude Edinburg, Brookline, Mass., Feb. 1971; given to the Art Institute of Chicago, 1998.",
    "edition": null,
    "publishing_verification_level": "Web Cataloged",
    "internal_department_id": 3,
    "fiscal_year": 1998,
    "fiscal_year_deaccession": null,
    "is_public_domain": true,
    "is_zoomable": true,
    "max_zoom_window_size": -1,
    "copyright_notice": null,
    "has_multimedia_resources": false,
    "has_educational_resources": false,
    "has_advanced_imaging": false,
    "colorfulness": 20.0618,
    "color": {
        "h": 45,
        "l": 43,
        "s": 6,
        "percentage": 0.4530715352539704,
        "population": 5160
    },
    "latitude": null,
    "longitude": null,
    "latlon": null,
    "is_on_view": false,
    "on_loan_display": null,
    "gallery_title": null,
    "gallery_id": null,
    "nomisma_id": null,
    "artwork_type_title": "Drawing and Watercolor",
    "artwork_type_id": 14,
    "department_title": "Prints and Drawings",
    "department_id": "PC-13",
    "artist_id": 41179,
    "artist_title": "Denys Calvaert",
    "alt_artist_ids": [],
    "artist_ids": [
        41179
    ],
    "artist_titles": [
        "Denys Calvaert"
    ],
    "category_ids": [
        "PC-13"
    ],
    "category_titles": [
        "Prints and Drawings"
    ],
    "term_titles": [
        "chalk",
        "Virgin and child/Madonna and child",
        "paper (fiber product)",
        "black chalk",
        "chalk",
        "inorganic material",
        "Christian subjects",
        "mythology",
        "prints and drawings",
        "diamond shapes",
        "saints",
        "drawings (visual works)",
        "prints and drawing"
    ],
    "style_id": null,
    "style_title": null,
    "alt_style_ids": [],
    "style_ids": [],
    "style_titles": [],
    "classification_id": "TM-209",
    "classification_title": "chalk",
    "alt_classification_ids": [
        "TM-5",
        "TM-4"
    ],
    "classification_ids": [
        "TM-209",
        "TM-5",
        "TM-4"
    ],
    "classification_titles": [
        "chalk",
        "drawings (visual works)",
        "prints and drawing"
    ],
    "subject_id": "TM-8779",
    "alt_subject_ids": [
        "TM-8767",
        "TM-8766",
        "TM-8650",
        "TM-8782",
        "TM-8827"
    ],
    "subject_ids": [
        "TM-8779",
        "TM-8767",
        "TM-8766",
        "TM-8650",
        "TM-8782",
        "TM-8827"
    ],
    "subject_titles": [
        "Virgin and child/Madonna and child",
        "Christian subjects",
        "mythology",
        "prints and drawings",
        "diamond shapes",
        "saints"
    ],
    "material_id": "TM-2982",
    "alt_material_ids": [
        "TM-2414",
        "TM-3782",
        "TM-2600"
    ],
    "material_ids": [
        "TM-2982",
        "TM-2414",
        "TM-3782",
        "TM-2600"
    ],
    "material_titles": [
        "paper (fiber product)",
        "black chalk",
        "chalk",
        "inorganic material"
    ],
    "technique_id": null,
    "alt_technique_ids": [],
    "technique_ids": [],
    "technique_titles": [],
    "theme_titles": [],
    "image_id": "8edbe464-c9f9-5f29-e54f-aa8bebb82e2b",
    "alt_image_ids": [
        "cf1d5392-bd47-b921-0689-21444d472b32",
        "622882b2-26ed-31ce-1b04-d7963d4fc69e",
        "8d87d22c-c0a2-c377-4c80-eba254c19fcf"
    ],
    "document_ids": [],
    "sound_ids": [],
    "video_ids": [],
    "text_ids": [],
    "section_ids": [],
    "section_titles": [],
    "site_ids": [],
    "suggest_autocomplete_all": [
        {
            "input": [
                "1998.99"
            ],
            "contexts": {
                "groupings": [
                    "accession"
                ]
            }
        },
        {
            "input": [
                "Saint Francis of Assisi Adoring the Virgin and Child"
            ],
            "weight": 389,
            "contexts": {
                "groupings": [
                    "title"
                ]
            }
        }
    ],
    "source_updated_at": "2022-09-21T19:19:16-05:00",
    "updated_at": "2023-04-10T08:02:17-05:00",
    "timestamp": "2023-09-24T01:26:50-05:00"
}