{
    "id": 27643,
    "api_model": "artworks",
    "api_link": "https://api.artic.edu/api/v1/artworks/27643",
    "is_boosted": false,
    "title": "Candelabra",
    "alt_titles": null,
    "thumbnail": {
        "lqip": "data:image/gif;base64,R0lGODlhAwAFAPMAAIp8aqOblaSioaemqK2vs66vtLO0uLS1uc/P09LR1d7Y0NvY1uXi4ebk4+vp5wAAACH5BAAAAAAALAAAAAADAAUAAAQLsAxyhEEhLcCachEAOw==",
        "width": 1373,
        "height": 2250,
        "alt_text": "A work made of clear and blue glass, gilding and bronze mounts."
    },
    "main_reference_number": "1967.403",
    "has_not_been_viewed_much": true,
    "boost_rank": null,
    "date_start": 1780,
    "date_end": 1800,
    "date_display": "1780/1800",
    "date_qualifier_title": "",
    "date_qualifier_id": null,
    "artist_display": "England",
    "place_of_origin": "England",
    "description": null,
    "dimensions": "H.: 31.4 cm (12 3/8 in.)",
    "dimensions_detail": [
        {
            "depth_cm": 0,
            "depth_in": 0,
            "width_cm": 0,
            "width_in": 0,
            "height_cm": 31.4,
            "height_in": 12.375,
            "diameter_cm": 0,
            "diameter_in": 0,
            "clarification": null
        }
    ],
    "medium_display": "Clear and blue glass, gilding and bronze mounts",
    "inscriptions": null,
    "credit_line": "Purchased with funds provided by Mrs. Josephine P. Albright",
    "catalogue_display": null,
    "publication_history": null,
    "exhibition_history": null,
    "provenance_text": null,
    "edition": null,
    "publishing_verification_level": "Web Basic",
    "internal_department_id": 6,
    "fiscal_year": 1968,
    "fiscal_year_deaccession": null,
    "is_public_domain": true,
    "is_zoomable": true,
    "max_zoom_window_size": -1,
    "copyright_notice": null,
    "has_multimedia_resources": false,
    "has_educational_resources": false,
    "has_advanced_imaging": false,
    "colorfulness": 17.7351,
    "color": {
        "h": 37,
        "l": 67,
        "s": 63,
        "percentage": 0.0034358859388944865,
        "population": 40
    },
    "latitude": null,
    "longitude": null,
    "latlon": null,
    "is_on_view": false,
    "on_loan_display": null,
    "gallery_title": null,
    "gallery_id": null,
    "nomisma_id": null,
    "artwork_type_title": "Glass",
    "artwork_type_id": 37,
    "department_title": "Applied Arts of Europe",
    "department_id": "PC-9",
    "artist_id": null,
    "artist_title": null,
    "alt_artist_ids": [],
    "artist_ids": [],
    "artist_titles": [],
    "category_ids": [
        "PC-9"
    ],
    "category_titles": [
        "Applied Arts of Europe"
    ],
    "term_titles": [
        "candleholder - candlestick",
        "bronze",
        "Neoclassicism",
        "candleholder",
        "bronze",
        "european",
        "metalwork",
        "european decorative arts",
        "glass"
    ],
    "style_id": "TM-5983",
    "style_title": "Neoclassicism",
    "alt_style_ids": [
        "TM-4703"
    ],
    "style_ids": [
        "TM-5983",
        "TM-4703"
    ],
    "style_titles": [
        "Neoclassicism",
        "european"
    ],
    "classification_id": "TM-333",
    "classification_title": "candleholder - candlestick",
    "alt_classification_ids": [
        "TM-11771",
        "TM-28",
        "TM-29",
        "TM-1394",
        "TM-85"
    ],
    "classification_ids": [
        "TM-333",
        "TM-11771",
        "TM-28",
        "TM-29",
        "TM-1394",
        "TM-85"
    ],
    "classification_titles": [
        "candleholder - candlestick",
        "candleholder",
        "bronze",
        "metalwork",
        "european decorative arts",
        "glass"
    ],
    "subject_id": null,
    "alt_subject_ids": [],
    "subject_ids": [],
    "subject_titles": [],
    "material_id": "TM-2430",
    "alt_material_ids": [],
    "material_ids": [
        "TM-2430"
    ],
    "material_titles": [
        "bronze"
    ],
    "technique_id": null,
    "alt_technique_ids": [],
    "technique_ids": [],
    "technique_titles": [],
    "theme_titles": [],
    "image_id": "0ec6b5c9-cc9a-69e8-9c68-eb0a532b948d",
    "alt_image_ids": [],
    "document_ids": [],
    "sound_ids": [],
    "video_ids": [],
    "text_ids": [],
    "section_ids": [],
    "section_titles": [],
    "site_ids": [],
    "suggest_autocomplete_all": [
        {
            "input": [
                "1967.403"
            ],
            "contexts": {
                "groupings": [
                    "accession"
                ]
            }
        },
        {
            "input": [
                "Candelabra"
            ],
            "weight": 7,
            "contexts": {
                "groupings": [
                    "title"
                ]
            }
        }
    ],
    "source_updated_at": "2023-06-07T09:22:06-05:00",
    "updated_at": "2023-06-07T09:58:13-05:00",
    "timestamp": "2023-09-24T00:32:39-05:00"
}