{
    "id": "3e1ff341-40cd-aaf9-148c-c7112561d519",
    "lake_guid": "3e1ff341-40cd-aaf9-148c-c7112561d519",
    "api_model": "images",
    "api_link": "https://api.artic.edu/api/v1/images/3e1ff341-40cd-aaf9-148c-c7112561d519",
    "title": "J6625-int",
    "type": "image",
    "alt_text": null,
    "content": null,
    "is_multimedia_resource": false,
    "is_educational_resource": false,
    "is_teacher_resource": false,
    "credit_line": null,
    "content_e_tag": "1a713e691d1955565c463821ec4509a3",
    "iiif_url": "/3e1ff341-40cd-aaf9-148c-c7112561d519",
    "width": 5316,
    "height": 8153,
    "lqip": "data:image/gif;base64,R0lGODlhAwAFAPMAAH9sYI17bZ6LeaGPfamSeKqUequWfa2ahLSegLWih7+qib2oi8SxlMezlQAAAAAAACH5BAAAAAAALAAAAAADAAUAAAQL0Cx1RhOBgZAKQREAOw==",
    "colorfulness": 0,
    "color": {
        "h": 37,
        "l": 73,
        "s": 34,
        "percentage": 0.001356672155190005,
        "population": 588
    },
    "fingerprint": null,
    "ahash": null,
    "phash": null,
    "artwork_ids": [
        60119
    ],
    "artwork_titles": [
        "Portrait of Sailor"
    ],
    "source_updated_at": "2022-04-12T08:25:02-05:00",
    "updated_at": "2022-04-12T08:26:34-05:00",
    "timestamp": "2023-09-24T02:10:54-05:00"
}