{
    "id": "54cc3954-10d5-4816-4dce-78f3f991bbc7",
    "lake_guid": "54cc3954-10d5-4816-4dce-78f3f991bbc7",
    "api_model": "images",
    "api_link": "https://api.artic.edu/api/v1/images/54cc3954-10d5-4816-4dce-78f3f991bbc7",
    "title": "2023.616-pm",
    "type": "image",
    "alt_text": null,
    "content": null,
    "is_multimedia_resource": false,
    "is_educational_resource": false,
    "is_teacher_resource": false,
    "credit_line": null,
    "content_e_tag": "1691be8c14f4f15af8f37fd783622bb8",
    "iiif_url": "/54cc3954-10d5-4816-4dce-78f3f991bbc7",
    "width": 6290,
    "height": 9435,
    "lqip": "data:image/gif;base64,R0lGODlhAwAFAPMAAHRrXH13bYl/boyCc5OLfJaOgZ2Wi5+akqSbjaWdkaWfmquhkqSgmrOqmce/rwAAACH5BAAAAAAALAAAAAADAAUAAAQLMBFXAFoitGEUOxEAOw==",
    "colorfulness": 0,
    "color": {
        "h": 232,
        "l": 53,
        "s": 37,
        "percentage": 2.6960468370736773e-5,
        "population": 16
    },
    "fingerprint": null,
    "ahash": null,
    "phash": null,
    "artwork_ids": [
        268218
    ],
    "artwork_titles": [
        "Joseph, from The Twelve Sons of Jacob"
    ],
    "source_updated_at": "2023-08-23T09:15:04-05:00",
    "updated_at": "2023-08-23T09:15:50-05:00",
    "timestamp": "2023-09-24T02:11:13-05:00"
}