{
    "id": "ee41a5be-0ef1-97af-78b7-8ff198ee8aff",
    "lake_guid": "ee41a5be-0ef1-97af-78b7-8ff198ee8aff",
    "api_model": "images",
    "api_link": "https://api.artic.edu/api/v1/images/ee41a5be-0ef1-97af-78b7-8ff198ee8aff",
    "title": "IM048163",
    "type": "image",
    "alt_text": null,
    "content": null,
    "is_multimedia_resource": false,
    "is_educational_resource": false,
    "is_teacher_resource": false,
    "credit_line": null,
    "content_e_tag": "47534684b30be42798ad1beafe71a7ec",
    "iiif_url": "/ee41a5be-0ef1-97af-78b7-8ff198ee8aff",
    "width": 2656,
    "height": 7379,
    "lqip": "data:image/gif;base64,R0lGODlhAgAFAPMAAEtGQlhVUGFeWWNfWmxnYW1pZHBoYHBsZ3JuaXx1bgAAAAAAAAAAAAAAAAAAAAAAACH5BAAAAAAALAAAAAACAAUAAAQIMBkCjhgBlQgAOw==",
    "colorfulness": 0,
    "color": {
        "h": 37,
        "l": 59,
        "s": 5,
        "percentage": 0.01322541827426252,
        "population": 2592
    },
    "fingerprint": null,
    "ahash": null,
    "phash": null,
    "artwork_ids": [
        254389
    ],
    "artwork_titles": [
        "Toby Spiselman's Glove"
    ],
    "source_updated_at": "2021-07-08T12:31:34-05:00",
    "updated_at": "2021-07-08T12:35:50-05:00",
    "timestamp": "2023-09-24T02:10:33-05:00"
}