{
    "id": "50f51e4e-cff5-fcf0-d42e-d82d0b89d3c2",
    "lake_guid": "50f51e4e-cff5-fcf0-d42e-d82d0b89d3c2",
    "api_model": "texts",
    "api_link": "https://api.artic.edu/api/v1/texts/50f51e4e-cff5-fcf0-d42e-d82d0b89d3c2",
    "title": "AIC1906ArtsCraft5thAn_com.pdf",
    "type": "text",
    "alt_text": null,
    "content": "https://www.artic.edu/assets/50f51e4e-cff5-fcf0-d42e-d82d0b89d3c2",
    "is_multimedia_resource": false,
    "is_educational_resource": false,
    "is_teacher_resource": false,
    "credit_line": null,
    "content_e_tag": "6273bb98d3fdfd623c33782d0de02fc8",
    "artwork_ids": [],
    "artwork_titles": [],
    "source_updated_at": "2020-12-15T13:20:38-06:00",
    "updated_at": "2020-12-15T22:56:20-06:00",
    "timestamp": "2023-09-24T02:12:01-05:00"
}