{
    "id": "75797bd5-d6c3-0782-8de9-c08d4e63d961",
    "lake_guid": "75797bd5-d6c3-0782-8de9-c08d4e63d961",
    "api_model": "texts",
    "api_link": "https://api.artic.edu/api/v1/texts/75797bd5-d6c3-0782-8de9-c08d4e63d961",
    "title": "AIC1901LeftwichDodge_comb.pdf",
    "type": "text",
    "alt_text": null,
    "content": "https://www.artic.edu/assets/75797bd5-d6c3-0782-8de9-c08d4e63d961",
    "is_multimedia_resource": false,
    "is_educational_resource": false,
    "is_teacher_resource": false,
    "credit_line": null,
    "content_e_tag": "c207ba2227b28ad8a433b1d58be88b2d",
    "artwork_ids": [],
    "artwork_titles": [],
    "source_updated_at": "2020-12-15T13:20:58-06:00",
    "updated_at": "2020-12-15T22:56:06-06:00",
    "timestamp": "2023-09-24T02:12:03-05:00"
}