{
    "id": 4478,
    "api_model": "exhibitions",
    "api_link": "https://api.artic.edu/api/v1/exhibitions/4478",
    "title": "Memorial Collection of Works by Walter Shirlaw",
    "is_featured": false,
    "position": -1,
    "short_description": null,
    "web_url": null,
    "image_url": null,
    "status": "Closed",
    "aic_start_at": "1911-01-03T00:00:00-06:00",
    "aic_end_at": "1911-01-22T00:00:00-06:00",
    "gallery_id": null,
    "gallery_title": null,
    "artwork_ids": [],
    "artwork_titles": [],
    "artist_ids": [],
    "site_ids": [],
    "image_id": null,
    "alt_image_ids": [],
    "document_ids": [
        "be8dab05-16c2-4196-8f16-8c2b8d1aa45c"
    ],
    "suggest_autocomplete_all": {
        "input": [
            "Memorial Collection of Works by Walter Shirlaw"
        ],
        "contexts": {
            "groupings": [
                "title"
            ]
        }
    },
    "source_updated_at": "1976-09-02T11:20:00-05:00",
    "updated_at": "2020-12-15T10:20:55-06:00",
    "timestamp": "2023-09-24T02:01:24-05:00"
}