{
    "id": 6310,
    "api_model": "exhibitions",
    "api_link": "https://api.artic.edu/api/v1/exhibitions/6310",
    "title": "American Exhibition 50th Annual : Half a Century of American Art, 1888-1938",
    "is_featured": false,
    "position": -1,
    "short_description": null,
    "web_url": null,
    "image_url": null,
    "status": "Closed",
    "aic_start_at": "1939-11-16T00:00:00-06:00",
    "aic_end_at": "1940-01-07T00:00:00-06:00",
    "gallery_id": null,
    "gallery_title": null,
    "artwork_ids": [],
    "artwork_titles": [],
    "artist_ids": [],
    "site_ids": [],
    "image_id": "a5d415fc-0d9e-cd7e-e6bf-7bc6a1836ea7",
    "alt_image_ids": [],
    "document_ids": [
        "d2a18264-7fe5-b4ab-89cf-3c07c5d47dc6"
    ],
    "suggest_autocomplete_all": {
        "input": [
            "American Exhibition 50th Annual : Half a Century of American Art, 1888-1938"
        ],
        "contexts": {
            "groupings": [
                "title"
            ]
        }
    },
    "source_updated_at": "1976-09-02T11:20:00-05:00",
    "updated_at": "2020-12-15T10:17:50-06:00",
    "timestamp": "2023-09-24T02:01:46-05:00"
}