{
    "id": 8042,
    "api_model": "exhibitions",
    "api_link": "https://api.artic.edu/api/v1/exhibitions/8042",
    "title": "Graphic Tours: Travel and 19th c. French Works on Paper",
    "is_featured": false,
    "position": -1,
    "short_description": null,
    "web_url": null,
    "image_url": null,
    "status": "Closed",
    "aic_start_at": "1994-01-14T00:00:00-06:00",
    "aic_end_at": "1994-04-17T00:00:00-05:00",
    "gallery_id": null,
    "gallery_title": null,
    "artwork_ids": [],
    "artwork_titles": [],
    "artist_ids": [],
    "site_ids": [],
    "image_id": "b4ca569a-dffe-8914-9004-7568c928beb0",
    "alt_image_ids": [
        "10d5c88e-8f98-e1ec-ad00-df19aafe245d",
        "87921268-bc97-02f3-b21b-ee50d161d095",
        "7121b80c-33d6-55c6-797b-5ad6ae5bf9a9",
        "da4780a4-d087-7cdf-e9d0-4c9f1ee1f419"
    ],
    "document_ids": [],
    "suggest_autocomplete_all": {
        "input": [
            "Graphic Tours: Travel and 19th c. French Works on Paper"
        ],
        "contexts": {
            "groupings": [
                "title"
            ]
        }
    },
    "source_updated_at": "1976-09-02T11:20:00-05:00",
    "updated_at": "2020-12-15T10:14:00-06:00",
    "timestamp": "2023-09-24T02:02:10-05:00"
}