{
    "id": 8125,
    "api_model": "exhibitions",
    "api_link": "https://api.artic.edu/api/v1/exhibitions/8125",
    "title": "The Face of War: Picasso's \u201cWeeping Woman\u201d",
    "is_featured": false,
    "position": -1,
    "short_description": null,
    "web_url": null,
    "image_url": null,
    "status": "Closed",
    "aic_start_at": "1995-05-19T00:00:00-05:00",
    "aic_end_at": "1995-08-28T00:00:00-05:00",
    "gallery_id": null,
    "gallery_title": null,
    "artwork_ids": [],
    "artwork_titles": [],
    "artist_ids": [],
    "site_ids": [],
    "image_id": "b9f0bfdc-c79b-1c0e-d5b3-79cd127e8af9",
    "alt_image_ids": [
        "f6d9a4bf-df3e-52be-e5a5-e0930b763f03",
        "fbcfd514-620a-fc11-3885-2276dae0d7e6",
        "6e139169-fa58-54da-1072-5d5c1916f123"
    ],
    "document_ids": [],
    "suggest_autocomplete_all": {
        "input": [
            "The Face of War: Picasso's \u201cWeeping Woman\u201d"
        ],
        "contexts": {
            "groupings": [
                "title"
            ]
        }
    },
    "source_updated_at": "1976-09-02T11:20:00-05:00",
    "updated_at": "2020-12-15T10:13:44-06:00",
    "timestamp": "2023-09-24T02:02:11-05:00"
}