{
    "id": 9226,
    "api_model": "exhibitions",
    "api_link": "https://api.artic.edu/api/v1/exhibitions/9226",
    "title": "Sex",
    "is_featured": false,
    "position": -1,
    "short_description": "<p>Known for giving form and voice to the alienation of today\u2019s society, Anne Imhof presents a new installation for the museum that combines music, choreography, painting, and sculpture.</p>",
    "web_url": "https://nocache.www.artic.edu/exhibitions/9226/anne-imhof",
    "image_url": "https://artic-web.imgix.net/55d6ce11-0730-4a81-bfa7-77698f69b352/01_11A0822.jpg?auto=compress%2Cformat&fit=min&fm=jpg&q=80&rect=0%2C392%2C4843%2C2722",
    "status": "Confirmed",
    "aic_start_at": "2019-05-30T00:00:00-05:00",
    "aic_end_at": "2019-07-07T00:00:00-05:00",
    "gallery_id": 25467,
    "gallery_title": "Gallery 289",
    "artwork_ids": [],
    "artwork_titles": [],
    "artist_ids": [],
    "site_ids": [],
    "image_id": null,
    "alt_image_ids": [],
    "document_ids": [],
    "suggest_autocomplete_all": {
        "input": [
            "Sex"
        ],
        "contexts": {
            "groupings": [
                "title"
            ]
        }
    },
    "source_updated_at": "2019-06-12T12:16:59-05:00",
    "updated_at": "2023-09-23T23:43:25-05:00",
    "timestamp": "2023-09-24T02:02:29-05:00"
}