{
    "id": "4edd1429-9083-655a-a73d-7ae3af84e180",
    "lake_guid": "4edd1429-9083-655a-a73d-7ae3af84e180",
    "api_model": "sounds",
    "api_link": "https://api.artic.edu/api/v1/sounds/4edd1429-9083-655a-a73d-7ae3af84e180",
    "title": "Audio Lecture: Tradition and Innovation\u2014Artist Olowe of Ise",
    "type": "sound",
    "alt_text": null,
    "content": "https://www.artic.edu/assets/4edd1429-9083-655a-a73d-7ae3af84e180",
    "is_multimedia_resource": false,
    "is_educational_resource": false,
    "is_teacher_resource": false,
    "credit_line": null,
    "content_e_tag": "f104319d40a147c9c8a462c4a9616ec9",
    "artwork_ids": [],
    "artwork_titles": [],
    "source_updated_at": "2020-12-15T13:21:27-06:00",
    "updated_at": "2020-12-15T22:57:07-06:00",
    "timestamp": "2023-09-24T02:11:55-05:00"
}